.gitignore
LICENSE
README.md
setup.cfg
setup.py
tests/test_base.py
tests/configs/test1.conf
toolconfig/__init__.py
toolconfig.egg-info/PKG-INFO
toolconfig.egg-info/SOURCES.txt
toolconfig.egg-info/dependency_links.txt
toolconfig.egg-info/top_level.txt