Metadata-Version: 1.1
Name: toolconfig
Version: 0.0.2
Summary: JSON config helper
Home-page: https://github.com/doctaweeks/toolconfig
Author: Daniel M. Weeks
Author-email: dan@danweeks.net
License: GPL-2
Keywords: json config expansion
Platform: UNKNOWN
Classifier: Development Status :: 3 - Alpha
Classifier: License :: OSI Approved :: GNU General Public License v2 (GPLv2)
Classifier: Topic :: Software Development :: Libraries
Classifier: Topic :: Utilities
